stroke_prediction/__init__.py
stroke_prediction/data_processing.py
stroke_prediction/inference.py
stroke_prediction/train.py
stroke_pred_p0w11-0.5.dist-info/LICENSE
stroke_pred_p0w11-0.5.dist-info/METADATA
stroke_pred_p0w11-0.5.dist-info/WHEEL
stroke_pred_p0w11-0.5.dist-info/top_level.txt
stroke_pred_p0w11-0.5.dist-info/RECORD
